AUTHORS.rst
MANIFEST.in
README.rst
requirements.pip
setup.cfg
setup.py
jinjaconfig/__init__.py
jinjaconfig.egg-info/PKG-INFO
jinjaconfig.egg-info/SOURCES.txt
jinjaconfig.egg-info/dependency_links.txt
jinjaconfig.egg-info/entry_points.txt
jinjaconfig.egg-info/requires.txt
jinjaconfig.egg-info/top_level.txt
tests/__init__.py