Metadata-Version: 1.1
Name: jinjaconfig
Version: 0.1
Summary: A jinja2 renderer receiving a JSON string from commandline. Useful for generating config     files in deployment enviroments
Home-page: https://bitbucket.org/luisfernando/jinjaconfig
Author: Luis Fernando Barrera
Author-email: luisfernando@informind.com
License: MIT
Platform: UNKNOWN
Classifier: Programming Language :: Python
Classifier: License :: OSI Approved :: MIT License
Classifier: Development Status :: 3 - Alpha
Classifier: Operating System :: OS Independent
Classifier: Intended Audience :: Developers
Classifier: Topic :: Internet :: WWW/HTTP :: Dynamic Content
